scrapegraph_py/__init__.py
scrapegraph_py/async_client.py
scrapegraph_py/client.py
scrapegraph_py/config.py
scrapegraph_py/exceptions.py
scrapegraph_py/logger.py
scrapegraph_py/models/__init__.py
scrapegraph_py/models/agenticscraper.py
scrapegraph_py/models/crawl.py
scrapegraph_py/models/feedback.py
scrapegraph_py/models/markdownify.py
scrapegraph_py/models/scheduled_jobs.py
scrapegraph_py/models/schema.py
scrapegraph_py/models/scrape.py
scrapegraph_py/models/searchscraper.py
scrapegraph_py/models/sitemap.py
scrapegraph_py/models/smartscraper.py
scrapegraph_py/utils/__init__.py
scrapegraph_py/utils/helpers.py
scrapegraph_py-1.41.1.dist-info/METADATA
scrapegraph_py-1.41.1.dist-info/WHEEL
scrapegraph_py-1.41.1.dist-info/RECORD
