Metadata-Version: 2.3
Name: scrapegraph_py
Version: 1.41.1
Summary: ScrapeGraph Python SDK for API
Author-email: Marco Vinciguerra <mvincig11@gmail.com>, Lorenzo Padoan <lorenzo.padoan977@gmail.com>
License: MIT
Keywords: ai,api,artificial intelligence,gpt,graph,machine learning,natural language processing,nlp,openai,scraping,sdk,web scraping tool,webscraping
Classifier: Intended Audience :: Developers
Classifier: Operating System :: OS Independent
Classifier: Programming Language :: Python :: 3
Classifier: Topic :: Software Development :: Libraries :: Python Modules
Requires-Python: <4.0,>=3.10
Requires-Dist: aiohttp>=3.10
Requires-Dist: beautifulsoup4>=4.12.3
Requires-Dist: pydantic>=2.10.2
Requires-Dist: python-dotenv>=1.0.1
Requires-Dist: requests>=2.32.3
Provides-Extra: docs
Requires-Dist: furo==2024.5.6; extra == 'docs'
Requires-Dist: sphinx==6.0; extra == 'docs'
